<Properties StartupConfiguration="{AF84BF44-527C-DF8C-5939-B48FC507B75A}|">
  <MonoDevelop.Ide.Workbench ActiveDocument="Assets/Sprites/TuturialEnemy/EnemyScript.cs">
    <Files>
      <File FileName="Assets/Sprites/Player/PlayerScripts/PlayerController.cs" Line="32" Column="44" />
      <File FileName="Assets/Sprites/Player/PlayerScripts/PlayerMovement.cs" Line="86" Column="36" />
      <File FileName="Assets/Sprites/Player/PlayerScripts/PlayerAttack.cs" Line="31" Column="1" />
      <File FileName="Assets/Sprites/Player/PlayerScripts/AttackTrigger.cs" Line="31" Column="1" />
      <File FileName="Assets/Sprites/TuturialEnemy/EnemyScript.cs" Line="7" Column="1" />
    </Files>
    <Pads>
      <Pad Id="ProjectPad">
        <State name="__root__">
          <Node name="MajorProjectMetroidVania" expanded="True">
            <Node name="Assets" expanded="True">
              <Node name="Scripts" expanded="True" />
              <Node name="Sprites" expanded="True">
                <Node name="Player" expanded="True">
                  <Node name="PlayerScripts" expanded="True" />
                </Node>
                <Node name="TuturialEnemy" expanded="True">
                  <Node name="EnemyScript.cs" selected="True" />
                </Node>
              </Node>
            </Node>
          </Node>
        </State>
      </Pad>
    </Pads>
  </MonoDevelop.Ide.Workbench>
  <MonoDevelop.Ide.DebuggingService.PinnedWatches />
  <MonoDevelop.Ide.Workspace ActiveConfiguration="Debug" />
  <MonoDevelop.Ide.ItemProperties.Assembly-CSharp PreferredExecutionTarget="eb3585b7-0a7b-48f1-bf06-e8d923b3663a" />
  <MonoDevelop.Ide.DebuggingService.Breakpoints>
    <BreakpointStore />
  </MonoDevelop.Ide.DebuggingService.Breakpoints>
  <MultiItemStartupConfigurations />
</Properties>